pyqt_notifier/__init__.py
pyqt_notifier/pyqtNotifier.py
pyqt_notifier/ico/__init__.py
pyqt_notifier/ico/close.svg
pyqt_notifier-0.0.13.dist-info/LICENSE
pyqt_notifier-0.0.13.dist-info/METADATA
pyqt_notifier-0.0.13.dist-info/WHEEL
pyqt_notifier-0.0.13.dist-info/top_level.txt
pyqt_notifier-0.0.13.dist-info/RECORD
