Metadata-Version: 2.1
Name: pyqt-notifier
Version: 0.0.13
Summary: PyQt notifier which shows at bottom right of the desktop screen
Home-page: https://github.com/yjg30737/pyqt-notifier.git
Author: Jung Gyu Yoon
Author-email: yjg30737@gmail.com
License: MIT
Platform: UNKNOWN
License-File: LICENSE
Requires-Dist: PyQt5 (>=5.8)
Requires-Dist: pyqt-svg-button (>=0.0.1)
